timeout_function_decorator/__init__.py
timeout_function_decorator/timeout_decorator.py
timeout_function_decorator-2.0.0.dist-info/LICENSE
timeout_function_decorator-2.0.0.dist-info/METADATA
timeout_function_decorator-2.0.0.dist-info/WHEEL
timeout_function_decorator-2.0.0.dist-info/top_level.txt
timeout_function_decorator-2.0.0.dist-info/RECORD
